odoo/addons/web_view_leaflet_map/README.rst
odoo/addons/web_view_leaflet_map/__init__.py
odoo/addons/web_view_leaflet_map/__manifest__.py
odoo/addons/web_view_leaflet_map/hooks.py
odoo/addons/web_view_leaflet_map/data/ir_config_parameter.xml
odoo/addons/web_view_leaflet_map/demo/ir_config_parameter.xml
odoo/addons/web_view_leaflet_map/i18n/fr.po
odoo/addons/web_view_leaflet_map/i18n/web_view_leaflet_map.pot
odoo/addons/web_view_leaflet_map/models/__init__.py
odoo/addons/web_view_leaflet_map/models/ir_act_window_view.py
odoo/addons/web_view_leaflet_map/models/ir_http.py
odoo/addons/web_view_leaflet_map/models/ir_ui_view.py
odoo/addons/web_view_leaflet_map/models/res_users.py
odoo/addons/web_view_leaflet_map/readme/CONFIGURE.rst
odoo/addons/web_view_leaflet_map/readme/CONTRIBUTORS.rst
odoo/addons/web_view_leaflet_map/readme/CREDITS.rst
odoo/addons/web_view_leaflet_map/readme/DESCRIPTION.rst
odoo/addons/web_view_leaflet_map/readme/DEVELOP.rst
odoo/addons/web_view_leaflet_map/readme/ROADMAP.rst
odoo/addons/web_view_leaflet_map/static/description/icon.png
odoo/addons/web_view_leaflet_map/static/description/index.html
odoo/addons/web_view_leaflet_map/static/description/res_partner_map_1.png
odoo/addons/web_view_leaflet_map/static/description/res_partner_map_2.png
odoo/addons/web_view_leaflet_map/static/lib/leaflet/leaflet.css
odoo/addons/web_view_leaflet_map/static/lib/leaflet/leaflet.js
odoo/addons/web_view_leaflet_map/static/lib/leaflet/leaflet.js.map
odoo/addons/web_view_leaflet_map/static/lib/leaflet/images/layers-2x.png
odoo/addons/web_view_leaflet_map/static/lib/leaflet/images/layers.png
odoo/addons/web_view_leaflet_map/static/lib/leaflet/images/marker-icon-2x.png
odoo/addons/web_view_leaflet_map/static/lib/leaflet/images/marker-icon.png
odoo/addons/web_view_leaflet_map/static/lib/leaflet/images/marker-shadow.png
odoo/addons/web_view_leaflet_map/static/src/css/web_view_leaflet_map.css
odoo/addons/web_view_leaflet_map/static/src/js/view/view_registry.js
odoo12_addon_web_view_leaflet_map-12.0.1.1.0.dist-info/METADATA
odoo12_addon_web_view_leaflet_map-12.0.1.1.0.dist-info/WHEEL
odoo12_addon_web_view_leaflet_map-12.0.1.1.0.dist-info/top_level.txt
odoo12_addon_web_view_leaflet_map-12.0.1.1.0.dist-info/RECORD
