Metadata-Version: 2.1
Name: odoo12-addon-web-view-leaflet-map
Version: 12.0.1.1.0
Summary: Integrate leaflet.js librairy with odoo and add new 'leaflet_map' view, to display markers.
Home-page: https://github.com/OCA/geospatial
Author: GRAP, Odoo Community Association (OCA)
Author-email: support@odoo-community.org
License: AGPL-3
Platform: UNKNOWN
Classifier: Programming Language :: Python
Classifier: Framework :: Odoo
Classifier: Framework :: Odoo :: 12.0
Classifier: License :: OSI Approved :: GNU Affero General Public License v3
Classifier: Development Status :: 3 - Alpha
Requires-Python: >=3.5
Requires-Dist: odoo <12.1dev,>=12.0a
